hmmlearn-0.3.3.dist-info/top_level.txt
hmmlearn-0.3.3.dist-info/RECORD
hmmlearn-0.3.3.dist-info/LICENSE.txt
hmmlearn-0.3.3.dist-info/METADATA
hmmlearn-0.3.3.dist-info/AUTHORS.rst
hmmlearn-0.3.3.dist-info/WHEEL
hmmlearn/utils.py
hmmlearn/_utils.py
hmmlearn/stats.py
hmmlearn/_kl_divergence.py
hmmlearn/__init__.py
hmmlearn/vhmm.py
hmmlearn/base.py
hmmlearn/_emissions.py
hmmlearn/_hmmc.cpython-313-x86_64-linux-gnu.so
hmmlearn/hmm.py
hmmlearn/tests/test_gaussian_hmm.py
hmmlearn/tests/test_multinomial_hmm.py
hmmlearn/tests/test_gmm_hmm_multisequence.py
hmmlearn/tests/test_poisson_hmm.py
hmmlearn/tests/test_utils.py
hmmlearn/tests/test_variational_categorical.py
hmmlearn/tests/conftest.py
hmmlearn/tests/__init__.py
hmmlearn/tests/test_variational_gaussian.py
hmmlearn/tests/test_kl_divergence.py
hmmlearn/tests/test_base.py
hmmlearn/tests/test_gmm_hmm.py
hmmlearn/tests/test_categorical_hmm.py
hmmlearn/tests/test_gmm_hmm_new.py
