Metadata-Version: 2.1
Name: hmmlearn
Version: 0.3.3
Summary: Hidden Markov Models in Python with scikit-learn like API
Author: David Cournapeau, Fabian Pedregosa, Gael Varoquaux, Sergei Lebedev, Antony Lee, Matthew Danielson
Project-URL: Repository, https://github.com/hmmlearn/hmmlearn
Classifier: Development Status :: 3 - Alpha
Classifier: License :: OSI Approved :: BSD License
Classifier: Intended Audience :: Developers
Classifier: Intended Audience :: Science/Research
Classifier: Topic :: Software Development
Classifier: Topic :: Scientific/Engineering
Classifier: Programming Language :: Python
Classifier: Programming Language :: Python :: 3
Requires-Python: >=3.8
License-File: LICENSE.txt
License-File: AUTHORS.rst
Requires-Dist: numpy>=1.10
Requires-Dist: scikit-learn!=0.22.0,>=0.16
Requires-Dist: scipy>=0.19
Provides-Extra: tests
Requires-Dist: pytest; extra == "tests"
Provides-Extra: docs
Requires-Dist: matplotlib; extra == "docs"
Requires-Dist: pydata_sphinx_theme; extra == "docs"
Requires-Dist: sphinx>=2.0; extra == "docs"
Requires-Dist: sphinx-gallery; extra == "docs"
